MANIFEST.in
README.rst
setup.py
common/__init__.py
common/admin.py
common/fields.py
common/managers.py
common/middleware.py
common/models.py
common/templatetags/__init__.py
common/templatetags/common.py
common/tests/__init__.py
common/tests/models.py
common/tests/schema.py
common/tests/tests.py
fh_django_common.egg-info/PKG-INFO
fh_django_common.egg-info/SOURCES.txt
fh_django_common.egg-info/dependency_links.txt
fh_django_common.egg-info/requires.txt
fh_django_common.egg-info/top_level.txt