Metadata-Version: 1.0
Name: fh-django-common
Version: 0.2.13
Summary: A Django app to provide common functionality in Django projects
Home-page: https://gitlab.com/futurehaus/django-common
Author: UNKNOWN
Author-email: UNKNOWN
License: UNKNOWN
Platform: UNKNOWN
